foliant/preprocessors/blockdiag.py
foliantcontrib_blockdiag-1.0.8.dist-info/LICENSE
foliantcontrib_blockdiag-1.0.8.dist-info/METADATA
foliantcontrib_blockdiag-1.0.8.dist-info/WHEEL
foliantcontrib_blockdiag-1.0.8.dist-info/top_level.txt
foliantcontrib_blockdiag-1.0.8.dist-info/RECORD
