Metadata-Version: 2.2
Name: foliantcontrib.blockdiag
Version: 1.0.8
Summary: Blockdiag preprocessor for Foliant doc maker. Supports blockdiag, seqdiag, actdiag, and nwdiag.
Home-page: https://github.com/foliant-docs/foliantcontrib.blockdiag
Author: Konstantin Molchanov
Author-email: moigagoo@live.com
License: MIT
Platform: any
Classifier: Development Status :: 5 - Production/Stable
Classifier: Environment :: Console
Classifier: Intended Audience :: Developers
Classifier: License :: OSI Approved :: MIT License
Classifier: Operating System :: OS Independent
Classifier: Programming Language :: Python
Classifier: Topic :: Documentation
Classifier: Topic :: Utilities
License-File: LICENSE
Requires-Dist: foliant>=1.0.8
Requires-Dist: Pillow==9.5.0
Requires-Dist: blockdiag[pdf]
Requires-Dist: seqdiag
Requires-Dist: actdiag
Requires-Dist: nwdiag
Dynamic: author
Dynamic: author-email
Dynamic: classifier
Dynamic: description
Dynamic: description-content-type
Dynamic: home-page
Dynamic: license
Dynamic: platform
Dynamic: requires-dist
Dynamic: summary
